mcsexps/1.py
mcsexps/2.py
mcsexps/3.py
mcsexps/4.py
mcsexps/5.py
mcsexps/6.py
mcsexps/7.py
mcsexps/__init__.py
mcsexps/__main__.py
mcsexps/setup.py
mscexps-1.0.0.dist-info/METADATA
mscexps-1.0.0.dist-info/WHEEL
mscexps-1.0.0.dist-info/top_level.txt
mscexps-1.0.0.dist-info/RECORD
